README.md
setup.py
simcubeltd_pulumi_nexus/__init__.py
simcubeltd_pulumi_nexus/_inputs.py
simcubeltd_pulumi_nexus/_utilities.py
simcubeltd_pulumi_nexus/get_nexus_anonymous.py
simcubeltd_pulumi_nexus/get_nexus_blobstore.py
simcubeltd_pulumi_nexus/get_nexus_blobstore_azure.py
simcubeltd_pulumi_nexus/get_nexus_blobstore_file.py
simcubeltd_pulumi_nexus/get_nexus_blobstore_group.py
simcubeltd_pulumi_nexus/get_nexus_blobstore_s3.py
simcubeltd_pulumi_nexus/get_nexus_privileges.py
simcubeltd_pulumi_nexus/get_nexus_repository.py
simcubeltd_pulumi_nexus/get_nexus_repository_apt_hosted.py
simcubeltd_pulumi_nexus/get_nexus_repository_apt_proxy.py
simcubeltd_pulumi_nexus/get_nexus_repository_docker_group.py
simcubeltd_pulumi_nexus/get_nexus_repository_docker_hosted.py
simcubeltd_pulumi_nexus/get_nexus_repository_docker_proxy.py
simcubeltd_pulumi_nexus/get_nexus_repository_list.py
simcubeltd_pulumi_nexus/get_nexus_repository_yum_group.py
simcubeltd_pulumi_nexus/get_nexus_repository_yum_hosted.py
simcubeltd_pulumi_nexus/get_nexus_repository_yum_proxy.py
simcubeltd_pulumi_nexus/get_nexus_routing_rule.py
simcubeltd_pulumi_nexus/get_nexus_security_anonymous.py
simcubeltd_pulumi_nexus/get_nexus_security_content_selector.py
simcubeltd_pulumi_nexus/get_nexus_security_ldap.py
simcubeltd_pulumi_nexus/get_nexus_security_realms.py
simcubeltd_pulumi_nexus/get_nexus_security_role.py
simcubeltd_pulumi_nexus/get_nexus_security_saml.py
simcubeltd_pulumi_nexus/get_nexus_security_user.py
simcubeltd_pulumi_nexus/get_nexus_security_user_token.py
simcubeltd_pulumi_nexus/get_nexus_user.py
simcubeltd_pulumi_nexus/nexus_anonymous.py
simcubeltd_pulumi_nexus/nexus_blobstore.py
simcubeltd_pulumi_nexus/nexus_blobstore_azure.py
simcubeltd_pulumi_nexus/nexus_blobstore_file.py
simcubeltd_pulumi_nexus/nexus_blobstore_group.py
simcubeltd_pulumi_nexus/nexus_blobstore_s3.py
simcubeltd_pulumi_nexus/nexus_content_selector.py
simcubeltd_pulumi_nexus/nexus_privilege.py
simcubeltd_pulumi_nexus/nexus_repository.py
simcubeltd_pulumi_nexus.egg-info/PKG-INFO
simcubeltd_pulumi_nexus.egg-info/SOURCES.txt
simcubeltd_pulumi_nexus.egg-info/dependency_links.txt
simcubeltd_pulumi_nexus.egg-info/not-zip-safe
simcubeltd_pulumi_nexus.egg-info/requires.txt
simcubeltd_pulumi_nexus.egg-info/top_level.txt
