Metadata-Version: 2.1
Name: simcubeltd-pulumi-nexus
Version: 1.0.0
Summary: A Pulumi package for creating and managing SonaType Nexus resources.
Home-page: https://github.com/SimCubeLtd/pulumi-nexus
License: MIT
Project-URL: Repository, https://github.com/SimCubeLtd/pulumi-nexus
Keywords: pulumi nexus category/cloud
Platform: UNKNOWN
